venue.S.HTML
vortexes/___objectives/itinerary - aspirations.S.HTML
vortexes/___objectives/itinerary.S.HTML
vortexes/___objectives/sequentials/sequentials.S.HTML
vortexes/___objectives/sporatic/TradingView Screen.png
vortexes/___objectives/sporatic/itinerary.S.HTML
vortexes/__bin/vortexes_1
vortexes/__data_nodes/moon/clique.py
vortexes/__data_nodes/moon/listing_status.csv
vortexes/__data_nodes/moon/mongo.S.HTML
vortexes/__init__.py
vortexes/_interfaces/clique/__init__.py
vortexes/_interfaces/clique/group/__init__.py
vortexes/_interfaces/sanic_trails/strails.S.HTML
vortexes/_status/DB/records.json
vortexes/_status/clouds_status.proc.py
vortexes/_status/status.proc.py
vortexes/_status/status_1.py
vortexes/adventures/adventures.S.HTML
vortexes/adventures/meter/meter.S.HTML
vortexes/charts/charts.s.HTML
vortexes/charts/plotly/plotly.s.HTML
vortexes/climate/__init__.py
vortexes/climate/climate.S.HTML
vortexes/clouds/AV/AV.s.HTML
vortexes/clouds/Alpaca/Alpaca.s.HTML
vortexes/clouds/Alpaca/_data_API/data.S.HTML
vortexes/clouds/Alpaca/_data_API/v2/stock/symbol/bars.py
vortexes/clouds/Alpaca/crypto/_status/API_status_1.py
vortexes/clouds/Alpaca/crypto/crypto.S.HTML
vortexes/clouds/Alpaca/crypto/retrieve.py
vortexes/clouds/Alpaca/crypto/structure_1.py
vortexes/clouds/Alpaca/options/options.S.HTML
vortexes/clouds/Alpaca/shares/retrieve_one.py
vortexes/clouds/Alpaca/shares/retrieve_spans.py
vortexes/clouds/Bybit/Bybit.S.HTML
vortexes/clouds/CCXT/CCXT.s.HTML
vortexes/clouds/CCXT/OHLCV/__init__.py
vortexes/clouds/CCXT/OHLCV/candles/__init__.py
vortexes/clouds/CCXT/OHLCV/candles/candles.s.HTML
vortexes/clouds/CCXT/OHLCV/candles_v1/__init__.py
vortexes/clouds/CCXT/OHLCV/candles_v1/candles.s.HTML
vortexes/clouds/CCXT/__init__.py
vortexes/clouds/CCXT/coinbase/coinbase.s.HTML
vortexes/clouds/CCXT/symbols/array.py
vortexes/clouds/Clouds Crypto.S.HTML
vortexes/clouds/Clouds Shares.S.HTML
vortexes/clouds/Clouds.S.HTML
vortexes/clouds/Coinbase/API/__init__.py
vortexes-0.0.1.dist-info/METADATA
vortexes-0.0.1.dist-info/WHEEL
vortexes-0.0.1.dist-info/entry_points.txt
vortexes-0.0.1.dist-info/RECORD
